EzScraper/__init__.py
EzScraper/table_to_csv.py
EzScraper-1.2.dist-info/METADATA
EzScraper-1.2.dist-info/WHEEL
EzScraper-1.2.dist-info/top_level.txt
EzScraper-1.2.dist-info/RECORD
