Metadata-Version: 2.1
Name: EzScraper
Version: 1.2
Summary: Scraping HTML Tables from websites to csv file
Author: Issam Haidaoui (issamoxix)
Author-email: <issamhaidaoui@gmail.com>
Keywords: python,Scraping,csv,Scraping Data,to csv file
Classifier: Development Status :: 1 - Planning
Classifier: Intended Audience :: Developers
Classifier: Programming Language :: Python :: 3
Classifier: Operating System :: Unix
Classifier: Operating System :: MacOS :: MacOS X
Classifier: Operating System :: Microsoft :: Windows
Requires-Dist: pandas
Requires-Dist: beautifulsoup4
Requires-Dist: requests
